<?xml version="1.0" encoding="UTF-8"?>
<configuration>
    <include resource="org/springframework/boot/logging/logback/defaults.xml"/>

    <!-- ── Appender: consola con traceId/spanId ──────────────────────────── -->
    <appender name="CONSOLE" class="ch.qos.logback.core.ConsoleAppender">
        <encoder>
            <pattern>%d{yyyy-MM-dd HH:mm:ss.SSS} [%property{spring.application.name},%X{traceId},%X{spanId}] %highlight(%-5level) %cyan(%logger{36}) - %msg%n</pattern>
        </encoder>
    </appender>

    <!-- ── Appender: Logstash TCP (JSON estructurado) ────────────────────── -->
    <appender name="LOGSTASH" class="net.logstash.logback.appender.LogstashTcpSocketAppender">
        <destination>localhost:5044</destination>
        <encoder class="net.logstash.logback.encoder.LoggingEventCompositeJsonEncoder">
            <providers>
                <timestamp/>
                <logLevel/>
                <loggerName/>
                <message/>
                <mdc/>                  <!-- incluye traceId y spanId del MDC -->
                <stackTrace/>
                <arguments/>
            </providers>
        </encoder>
    </appender>

    <!-- ── Perfil: default (sin argumento -Dspring.profiles.active) ──────── -->
    <springProfile name="default">
        <root level="INFO">
            <appender-ref ref="CONSOLE"/>
        </root>
    </springProfile>

    <!-- ── Perfil: dev / development ─────────────────────────────────────── -->
    <springProfile name="dev,development">
        <logger name="com.uade" level="DEBUG"/>
        <root level="INFO">
            <appender-ref ref="CONSOLE"/>
        </root>
    </springProfile>

    <!-- ── Perfil: elk — activa CONSOLA + LOGSTASH simultáneamente ───────── -->
    <springProfile name="elk">
        <logger name="com.uade" level="DEBUG"/>
        <root level="INFO">
            <appender-ref ref="CONSOLE"/>
            <appender-ref ref="LOGSTASH"/>
        </root>
    </springProfile>

</configuration>